{
  "places": [
    {
      "id": "P0",
      "name": "i8",
      "attributes": {
        "implemented_traits": [
          "Clone",
          "Copy",
          "Debug",
          "Eq",
          "Hash",
          "Ord",
          "PartialEq",
          "PartialOrd",
          "Send",
          "Sized",
          "Sync"
        ]
      }
    },
    {
      "id": "P1",
      "name": "i16",
      "attributes": {
        "implemented_traits": [
          "Clone",
          "Copy",
          "Debug",
          "Eq",
          "Hash",
          "Ord",
          "PartialEq",
          "PartialOrd",
          "Send",
          "Sized",
          "Sync"
        ]
      }
    },
    {
      "id": "P2",
      "name": "i32",
      "attributes": {
        "implemented_traits": [
          "Clone",
          "Copy",
          "Debug",
          "Eq",
          "Hash",
          "Ord",
          "PartialEq",
          "PartialOrd",
          "Send",
          "Sized",
          "Sync"
        ]
      }
    },
    {
      "id": "P3",
      "name": "i64",
      "attributes": {
        "implemented_traits": [
          "Clone",
          "Copy",
          "Debug",
          "Eq",
          "Hash",
          "Ord",
          "PartialEq",
          "PartialOrd",
          "Send",
          "Sized",
          "Sync"
        ]
      }
    },
    {
      "id": "P4",
      "name": "i128",
      "attributes": {
        "implemented_traits": [
          "Clone",
          "Copy",
          "Debug",
          "Eq",
          "Hash",
          "Ord",
          "PartialEq",
          "PartialOrd",
          "Send",
          "Sized",
          "Sync"
        ]
      }
    },
    {
      "id": "P5",
      "name": "isize",
      "attributes": {
        "implemented_traits": [
          "Clone",
          "Copy",
          "Debug",
          "Eq",
          "Hash",
          "Ord",
          "PartialEq",
          "PartialOrd",
          "Send",
          "Sized",
          "Sync"
        ]
      }
    },
    {
      "id": "P6",
      "name": "u8",
      "attributes": {
        "implemented_traits": [
          "Clone",
          "Copy",
          "Debug",
          "Eq",
          "Hash",
          "Ord",
          "PartialEq",
          "PartialOrd",
          "Send",
          "Sized",
          "Sync"
        ]
      }
    },
    {
      "id": "P7",
      "name": "u16",
      "attributes": {
        "implemented_traits": [
          "Clone",
          "Copy",
          "Debug",
          "Eq",
          "Hash",
          "Ord",
          "PartialEq",
          "PartialOrd",
          "Send",
          "Sized",
          "Sync"
        ]
      }
    },
    {
      "id": "P8",
      "name": "u32",
      "attributes": {
        "implemented_traits": [
          "Clone",
          "Copy",
          "Debug",
          "Eq",
          "Hash",
          "Ord",
          "PartialEq",
          "PartialOrd",
          "Send",
          "Sized",
          "Sync"
        ]
      }
    },
    {
      "id": "P9",
      "name": "u64",
      "attributes": {
        "implemented_traits": [
          "Clone",
          "Copy",
          "Debug",
          "Eq",
          "Hash",
          "Ord",
          "PartialEq",
          "PartialOrd",
          "Send",
          "Sized",
          "Sync"
        ]
      }
    },
    {
      "id": "P10",
      "name": "u128",
      "attributes": {
        "implemented_traits": [
          "Clone",
          "Copy",
          "Debug",
          "Eq",
          "Hash",
          "Ord",
          "PartialEq",
          "PartialOrd",
          "Send",
          "Sized",
          "Sync"
        ]
      }
    },
    {
      "id": "P11",
      "name": "usize",
      "attributes": {
        "implemented_traits": [
          "Clone",
          "Copy",
          "Debug",
          "Eq",
          "Hash",
          "Ord",
          "PartialEq",
          "PartialOrd",
          "Send",
          "Sized",
          "Sync"
        ]
      }
    },
    {
      "id": "P12",
      "name": "f32",
      "attributes": {
        "implemented_traits": [
          "Clone",
          "Copy",
          "Debug",
          "PartialEq",
          "PartialOrd",
          "Send",
          "Sized",
          "Sync"
        ]
      }
    },
    {
      "id": "P13",
      "name": "f64",
      "attributes": {
        "implemented_traits": [
          "Clone",
          "Copy",
          "Debug",
          "PartialEq",
          "PartialOrd",
          "Send",
          "Sized",
          "Sync"
        ]
      }
    },
    {
      "id": "P14",
      "name": "bool",
      "attributes": {
        "implemented_traits": [
          "Clone",
          "Copy",
          "Debug",
          "Eq",
          "Hash",
          "Ord",
          "PartialEq",
          "PartialOrd",
          "Send",
          "Sized",
          "Sync"
        ]
      }
    },
    {
      "id": "P15",
      "name": "char",
      "attributes": {
        "implemented_traits": [
          "Clone",
          "Copy",
          "Debug",
          "Eq",
          "Hash",
          "Ord",
          "PartialEq",
          "PartialOrd",
          "Send",
          "Sized",
          "Sync"
        ]
      }
    },
    {
      "id": "P16",
      "name": "str",
      "attributes": {
        "implemented_traits": [
          "Clone",
          "Debug",
          "Eq",
          "Hash",
          "Ord",
          "PartialEq",
          "PartialOrd",
          "Send",
          "Sync"
        ]
      }
    },
    {
      "id": "P17",
      "name": "Alphabet"
    },
    {
      "id": "P18",
      "name": "UnprintableByte"
    },
    {
      "id": "P19",
      "name": "ReservedByte"
    },
    {
      "id": "P20",
      "name": "Indifferent"
    },
    {
      "id": "P21",
      "name": "RequireNone"
    },
    {
      "id": "P22",
      "name": "InvalidByte"
    },
    {
      "id": "P23",
      "name": "DecodePaddingMode"
    },
    {
      "id": "P24",
      "name": "EncoderStringWriter"
    },
    {
      "id": "P25",
      "name": "DecodeSliceError"
    },
    {
      "id": "P26",
      "name": "GeneralPurposeConfig"
    },
    {
      "id": "P27",
      "name": "Base64Display"
    },
    {
      "id": "P28",
      "name": "InvalidPadding"
    },
    {
      "id": "P29",
      "name": "ParseAlphabetError"
    },
    {
      "id": "P30",
      "name": "GeneralPurpose"
    },
    {
      "id": "P31",
      "name": "InvalidLength"
    },
    {
      "id": "P32",
      "name": "DecoderReader"
    },
    {
      "id": "P33",
      "name": "DecodeError"
    },
    {
      "id": "P34",
      "name": "DecodeMetadata"
    },
    {
      "id": "P35",
      "name": "EncoderWriter"
    },
    {
      "id": "P36",
      "name": "OutputSliceTooSmall"
    },
    {
      "id": "P37",
      "name": "RequireCanonical"
    },
    {
      "id": "P38",
      "name": "InvalidLastSymbol"
    },
    {
      "id": "P39",
      "name": "EncodeSliceError"
    },
    {
      "id": "P40",
      "name": "DuplicatedByte"
    },
    {
      "id": "P41",
      "name": "U",
      "attributes": {
        "is_generic_parameter": true
      },
      "generic_owner_id": 263,
      "generic_owner_name": "DecodeError"
    },
    {
      "id": "P42",
      "name": "T",
      "attributes": {
        "is_generic_parameter": true
      },
      "generic_owner_id": 263,
      "generic_owner_name": "DecodeError"
    },
    {
      "id": "P43",
      "name": "Error>"
    },
    {
      "id": "P44",
      "name": "TypeId"
    },
    {
      "id": "P45",
      "name": "String"
    },
    {
      "id": "P46",
      "name": "Formatter"
    },
    {
      "id": "P47",
      "name": "Result"
    },
    {
      "id": "P48",
      "name": "U",
      "attributes": {
        "is_generic_parameter": true
      },
      "generic_owner_id": 326,
      "generic_owner_name": "ParseAlphabetError"
    },
    {
      "id": "P49",
      "name": "T",
      "attributes": {
        "is_generic_parameter": true
      },
      "generic_owner_id": 326,
      "generic_owner_name": "ParseAlphabetError"
    },
    {
      "id": "P50",
      "name": "U",
      "attributes": {
        "is_generic_parameter": true
      },
      "generic_owner_id": 260,
      "generic_owner_name": "EncodeSliceError"
    },
    {
      "id": "P51",
      "name": "T",
      "attributes": {
        "is_generic_parameter": true
      },
      "generic_owner_id": 260,
      "generic_owner_name": "EncodeSliceError"
    },
    {
      "id": "P52",
      "name": "[u8]"
    },
    {
      "id": "P53",
      "name": "U",
      "attributes": {
        "is_generic_parameter": true
      },
      "generic_owner_id": 268,
      "generic_owner_name": "DecodeSliceError"
    },
    {
      "id": "P54",
      "name": "T",
      "attributes": {
        "is_generic_parameter": true
      },
      "generic_owner_id": 268,
      "generic_owner_name": "DecodeSliceError"
    },
    {
      "id": "P55",
      "name": "Error + 'static)>"
    },
    {
      "id": "P56",
      "name": "U",
      "attributes": {
        "is_generic_parameter": true
      },
      "generic_owner_id": 172,
      "generic_owner_name": "GeneralPurposeConfig"
    },
    {
      "id": "P57",
      "name": "T",
      "attributes": {
        "is_generic_parameter": true
      },
      "generic_owner_id": 172,
      "generic_owner_name": "GeneralPurposeConfig"
    },
    {
      "id": "P58",
      "name": "U",
      "attributes": {
        "is_generic_parameter": true
      },
      "generic_owner_id": 214,
      "generic_owner_name": "DecodePaddingMode"
    },
    {
      "id": "P59",
      "name": "T",
      "attributes": {
        "is_generic_parameter": true
      },
      "generic_owner_id": 214,
      "generic_owner_name": "DecodePaddingMode"
    },
    {
      "id": "P60",
      "name": "Alphabet, ParseAlphabetError>"
    },
    {
      "id": "P61",
      "name": "U",
      "attributes": {
        "is_generic_parameter": true
      },
      "generic_owner_id": 170,
      "generic_owner_name": "Alphabet"
    },
    {
      "id": "P62",
      "name": "T",
      "attributes": {
        "is_generic_parameter": true
      },
      "generic_owner_id": 170,
      "generic_owner_name": "Alphabet"
    },
    {
      "id": "P63",
      "name": "U",
      "attributes": {
        "is_generic_parameter": true
      },
      "generic_owner_id": 303,
      "generic_owner_name": "DecodeMetadata"
    },
    {
      "id": "P64",
      "name": "T",
      "attributes": {
        "is_generic_parameter": true
      },
      "generic_owner_id": 303,
      "generic_owner_name": "DecodeMetadata"
    },
    {
      "id": "P65",
      "name": "U",
      "attributes": {
        "is_generic_parameter": true
      },
      "generic_owner_id": 169,
      "generic_owner_name": "GeneralPurpose"
    },
    {
      "id": "P66",
      "name": "T",
      "attributes": {
        "is_generic_parameter": true
      },
      "generic_owner_id": 169,
      "generic_owner_name": "GeneralPurpose"
    },
    {
      "id": "P67",
      "name": "Config"
    },
    {
      "id": "P68",
      "name": "Option"
    },
    {
      "id": "P69",
      "name": "()"
    }
  ],
  "tokens": [],
  "transitions": [
    {
      "id": "T0",
      "name": "borrow",
      "kind": "method",
      "inputs": [
        {
          "type": "&base64::decode::DecodeError",
          "name": "self",
          "mode": "&"
        }
      ],
      "generic_params": [
        "T"
      ]
    },
    {
      "id": "T1",
      "name": "borrow_mut",
      "kind": "method",
      "inputs": [
        {
          "type": "&mut base64::decode::DecodeError",
          "name": "self",
          "mode": "&mut"
        }
      ],
      "generic_params": [
        "T"
      ]
    },
    {
      "id": "T2",
      "name": "clone_to_uninit",
      "kind": "method",
      "inputs": [
        {
          "type": "*mut u8",
          "name": "dest",
          "mode": "*mut"
        },
        {
          "type": "&base64::decode::DecodeError",
          "name": "self",
          "mode": "&"
        }
      ],
      "generic_params": [
        "T"
      ]
    },
    {
      "id": "T3",
      "name": "into",
      "kind": "method",
      "inputs": [
        {
          "type": "base64::decode::DecodeError",
          "name": "self",
          "mode": "value"
        }
      ],
      "outputs": [
        {
          "type": "U",
          "mode": "value"
        }
      ],
      "generic_params": [
        "T",
        "U"
      ]
    },
    {
      "id": "T4",
      "name": "from",
      "kind": "method",
      "inputs": [
        {
          "type": "T",
          "name": "t",
          "mode": "value"
        }
      ],
      "outputs": [
        {
          "type": "T",
          "mode": "value"
        }
      ],
      "generic_params": [
        "T"
      ]
    },
    {
      "id": "T5",
      "name": "try_into",
      "kind": "method",
      "inputs": [
        {
          "type": "base64::decode::DecodeError",
          "name": "self",
          "mode": "value"
        }
      ],
      "outputs": [
        {
          "type": "Error>",
          "mode": "value"
        }
      ],
      "generic_params": [
        "T",
        "U"
      ]
    },
    {
      "id": "T6",
      "name": "try_from",
      "kind": "method",
      "inputs": [
        {
          "type": "U",
          "name": "value",
          "mode": "value"
        }
      ],
      "outputs": [
        {
          "type": "Error>",
          "mode": "value"
        }
      ],
      "generic_params": [
        "T",
        "U"
      ]
    },
    {
      "id": "T7",
      "name": "type_id",
      "kind": "method",
      "inputs": [
        {
          "type": "&base64::decode::DecodeError",
          "name": "self",
          "mode": "&"
        }
      ],
      "outputs": [
        {
          "type": "TypeId",
          "mode": "value"
        }
      ],
      "generic_params": [
        "T"
      ]
    },
    {
      "id": "T8",
      "name": "to_owned",
      "kind": "method",
      "inputs": [
        {
          "type": "&base64::decode::DecodeError",
          "name": "self",
          "mode": "&"
        }
      ],
      "outputs": [
        {
          "type": "T",
          "mode": "value"
        }
      ],
      "generic_params": [
        "T"
      ]
    },
    {
      "id": "T9",
      "name": "clone_into",
      "kind": "method",
      "inputs": [
        {
          "type": "&base64::decode::DecodeError",
          "name": "self",
          "mode": "&"
        }
      ],
      "generic_params": [
        "T"
      ]
    },
    {
      "id": "T10",
      "name": "to_string",
      "kind": "method",
      "inputs": [
        {
          "type": "&base64::decode::DecodeError",
          "name": "self",
          "mode": "&"
        }
      ],
      "outputs": [
        {
          "type": "String",
          "mode": "value"
        }
      ],
      "generic_params": [
        "T"
      ]
    },
    {
      "id": "T11",
      "name": "clone",
      "kind": "method",
      "inputs": [
        {
          "type": "&base64::decode::DecodeError",
          "name": "self",
          "mode": "&"
        }
      ],
      "outputs": [
        {
          "type": "DecodeError",
          "mode": "value"
        }
      ]
    },
    {
      "id": "T12",
      "name": "fmt",
      "kind": "method",
      "inputs": [
        {
          "type": "&mut $crate::fmt::Formatter<'_>",
          "name": "f",
          "mode": "&mut"
        },
        {
          "type": "&base64::decode::DecodeError",
          "name": "self",
          "mode": "&"
        }
      ],
      "outputs": [
        {
          "type": "Result",
          "mode": "value"
        }
      ]
    },
    {
      "id": "T13",
      "name": "eq",
      "kind": "method",
      "inputs": [
        {
          "type": "&DecodeError",
          "name": "other",
          "mode": "&"
        },
        {
          "type": "&base64::decode::DecodeError",
          "name": "self",
          "mode": "&"
        }
      ],
      "outputs": [
        {
          "type": "bool",
          "mode": "value"
        }
      ]
    },
    {
      "id": "T14",
      "name": "fmt",
      "kind": "method",
      "inputs": [
        {
          "type": "&mut fmt::Formatter<'_>",
          "name": "f",
          "mode": "&mut"
        },
        {
          "type": "&base64::decode::DecodeError",
          "name": "self",
          "mode": "&"
        }
      ],
      "outputs": [
        {
          "type": "Result",
          "mode": "value"
        }
      ]
    },
    {
      "id": "T15",
      "name": "from",
      "kind": "method",
      "inputs": [
        {
          "type": "DecodeError",
          "name": "e",
          "mode": "value"
        }
      ],
      "outputs": [
        {
          "type": "DecodeSliceError",
          "mode": "value"
        }
      ]
    },
    {
      "id": "T16",
      "name": "borrow",
      "kind": "method",
      "inputs": [
        {
          "type": "&base64::alphabet::ParseAlphabetError",
          "name": "self",
          "mode": "&"
        }
      ],
      "generic_params": [
        "T"
      ]
    },
    {
      "id": "T17",
      "name": "borrow_mut",
      "kind": "method",
      "inputs": [
        {
          "type": "&mut base64::alphabet::ParseAlphabetError",
          "name": "self",
          "mode": "&mut"
        }
      ],
      "generic_params": [
        "T"
      ]
    },
    {
      "id": "T18",
      "name": "into",
      "kind": "method",
      "inputs": [
        {
          "type": "base64::alphabet::ParseAlphabetError",
          "name": "self",
          "mode": "value"
        }
      ],
      "outputs": [
        {
          "type": "U",
          "mode": "value"
        }
      ],
      "generic_params": [
        "T",
        "U"
      ]
    },
    {
      "id": "T19",
      "name": "from",
      "kind": "method",
      "inputs": [
        {
          "type": "T",
          "name": "t",
          "mode": "value"
        }
      ],
      "outputs": [
        {
          "type": "T",
          "mode": "value"
        }
      ],
      "generic_params": [
        "T"
      ]
    },
    {
      "id": "T20",
      "name": "try_into",
      "kind": "method",
      "inputs": [
        {
          "type": "base64::alphabet::ParseAlphabetError",
          "name": "self",
          "mode": "value"
        }
      ],
      "outputs": [
        {
          "type": "Error>",
          "mode": "value"
        }
      ],
      "generic_params": [
        "T",
        "U"
      ]
    },
    {
      "id": "T21",
      "name": "try_from",
      "kind": "method",
      "inputs": [
        {
          "type": "U",
          "name": "value",
          "mode": "value"
        }
      ],
      "outputs": [
        {
          "type": "Error>",
          "mode": "value"
        }
      ],
      "generic_params": [
        "T",
        "U"
      ]
    },
    {
      "id": "T22",
      "name": "type_id",
      "kind": "method",
      "inputs": [
        {
          "type": "&base64::alphabet::ParseAlphabetError",
          "name": "self",
          "mode": "&"
        }
      ],
      "outputs": [
        {
          "type": "TypeId",
          "mode": "value"
        }
      ],
      "generic_params": [
        "T"
      ]
    },
    {
      "id": "T23",
      "name": "to_string",
      "kind": "method",
      "inputs": [
        {
          "type": "&base64::alphabet::ParseAlphabetError",
          "name": "self",
          "mode": "&"
        }
      ],
      "outputs": [
        {
          "type": "String",
          "mode": "value"
        }
      ],
      "generic_params": [
        "T"
      ]
    },
    {
      "id": "T24",
      "name": "fmt",
      "kind": "method",
      "inputs": [
        {
          "type": "&mut $crate::fmt::Formatter<'_>",
          "name": "f",
          "mode": "&mut"
        },
        {
          "type": "&base64::alphabet::ParseAlphabetError",
          "name": "self",
          "mode": "&"
        }
      ],
      "outputs": [
        {
          "type": "Result",
          "mode": "value"
        }
      ]
    },
    {
      "id": "T25",
      "name": "eq",
      "kind": "method",
      "inputs": [
        {
          "type": "&ParseAlphabetError",
          "name": "other",
          "mode": "&"
        },
        {
          "type": "&base64::alphabet::ParseAlphabetError",
          "name": "self",
          "mode": "&"
        }
      ],
      "outputs": [
        {
          "type": "bool",
          "mode": "value"
        }
      ]
    },
    {
      "id": "T26",
      "name": "fmt",
      "kind": "method",
      "inputs": [
        {
          "type": "&mut fmt::Formatter<'_>",
          "name": "f",
          "mode": "&mut"
        },
        {
          "type": "&base64::alphabet::ParseAlphabetError",
          "name": "self",
          "mode": "&"
        }
      ],
      "outputs": [
        {
          "type": "Result",
          "mode": "value"
        }
      ]
    },
    {
      "id": "T27",
      "name": "borrow",
      "kind": "method",
      "inputs": [
        {
          "type": "&base64::encode::EncodeSliceError",
          "name": "self",
          "mode": "&"
        }
      ],
      "generic_params": [
        "T"
      ]
    },
    {
      "id": "T28",
      "name": "borrow_mut",
      "kind": "method",
      "inputs": [
        {
          "type": "&mut base64::encode::EncodeSliceError",
          "name": "self",
          "mode": "&mut"
        }
      ],
      "generic_params": [
        "T"
      ]
    },
    {
      "id": "T29",
      "name": "clone_to_uninit",
      "kind": "method",
      "inputs": [
        {
          "type": "*mut u8",
          "name": "dest",
          "mode": "*mut"
        },
        {
          "type": "&base64::encode::EncodeSliceError",
          "name": "self",
          "mode": "&"
        }
      ],
      "generic_params": [
        "T"
      ]
    },
    {
      "id": "T30",
      "name": "into",
      "kind": "method",
      "inputs": [
        {
          "type": "base64::encode::EncodeSliceError",
          "name": "self",
          "mode": "value"
        }
      ],
      "outputs": [
        {
          "type": "U",
          "mode": "value"
        }
      ],
      "generic_params": [
        "T",
        "U"
      ]
    },
    {
      "id": "T31",
      "name": "from",
      "kind": "method",
      "inputs": [
        {
          "type": "T",
          "name": "t",
          "mode": "value"
        }
      ],
      "outputs": [
        {
          "type": "T",
          "mode": "value"
        }
      ],
      "generic_params": [
        "T"
      ]
    },
    {
      "id": "T32",
      "name": "try_into",
      "kind": "method",
      "inputs": [
        {
          "type": "base64::encode::EncodeSliceError",
          "name": "self",
          "mode": "value"
        }
      ],
      "outputs": [
        {
          "type": "Error>",
          "mode": "value"
        }
      ],
      "generic_params": [
        "T",
        "U"
      ]
    },
    {
      "id": "T33",
      "name": "try_from",
      "kind": "method",
      "inputs": [
        {
          "type": "U",
          "name": "value",
          "mode": "value"
        }
      ],
      "outputs": [
        {
          "type": "Error>",
          "mode": "value"
        }
      ],
      "generic_params": [
        "T",
        "U"
      ]
    },
    {
      "id": "T34",
      "name": "type_id",
      "kind": "method",
      "inputs": [
        {
          "type": "&base64::encode::EncodeSliceError",
          "name": "self",
          "mode": "&"
        }
      ],
      "outputs": [
        {
          "type": "TypeId",
          "mode": "value"
        }
      ],
      "generic_params": [
        "T"
      ]
    },
    {
      "id": "T35",
      "name": "to_owned",
      "kind": "method",
      "inputs": [
        {
          "type": "&base64::encode::EncodeSliceError",
          "name": "self",
          "mode": "&"
        }
      ],
      "outputs": [
        {
          "type": "T",
          "mode": "value"
        }
      ],
      "generic_params": [
        "T"
      ]
    },
    {
      "id": "T36",
      "name": "clone_into",
      "kind": "method",
      "inputs": [
        {
          "type": "&base64::encode::EncodeSliceError",
          "name": "self",
          "mode": "&"
        }
      ],
      "generic_params": [
        "T"
      ]
    },
    {
      "id": "T37",
      "name": "to_string",
      "kind": "method",
      "inputs": [
        {
          "type": "&base64::encode::EncodeSliceError",
          "name": "self",
          "mode": "&"
        }
      ],
      "outputs": [
        {
          "type": "String",
          "mode": "value"
        }
      ],
      "generic_params": [
        "T"
      ]
    },
    {
      "id": "T38",
      "name": "clone",
      "kind": "method",
      "inputs": [
        {
          "type": "&base64::encode::EncodeSliceError",
          "name": "self",
          "mode": "&"
        }
      ],
      "outputs": [
        {
          "type": "EncodeSliceError",
          "mode": "value"
        }
      ]
    },
    {
      "id": "T39",
      "name": "fmt",
      "kind": "method",
      "inputs": [
        {
          "type": "&mut $crate::fmt::Formatter<'_>",
          "name": "f",
          "mode": "&mut"
        },
        {
          "type": "&base64::encode::EncodeSliceError",
          "name": "self",
          "mode": "&"
        }
      ],
      "outputs": [
        {
          "type": "Result",
          "mode": "value"
        }
      ]
    },
    {
      "id": "T40",
      "name": "eq",
      "kind": "method",
      "inputs": [
        {
          "type": "&EncodeSliceError",
          "name": "other",
          "mode": "&"
        },
        {
          "type": "&base64::encode::EncodeSliceError",
          "name": "self",
          "mode": "&"
        }
      ],
      "outputs": [
        {
          "type": "bool",
          "mode": "value"
        }
      ]
    },
    {
      "id": "T41",
      "name": "fmt",
      "kind": "method",
      "inputs": [
        {
          "type": "&mut fmt::Formatter<'_>",
          "name": "f",
          "mode": "&mut"
        },
        {
          "type": "&base64::encode::EncodeSliceError",
          "name": "self",
          "mode": "&"
        }
      ],
      "outputs": [
        {
          "type": "Result",
          "mode": "value"
        }
      ]
    },
    {
      "id": "T42",
      "name": "new",
      "kind": "method",
      "inputs": [
        {
          "type": "&'a [u8]",
          "name": "bytes",
          "mode": "&"
        }
      ],
      "outputs": [
        {
          "type": "Base64Display",
          "mode": "value"
        }
      ],
      "generic_params": [
        "''a",
        "''e",
        "E: Engine"
      ]
    },
    {
      "id": "T43",
      "name": "borrow",
      "kind": "method",
      "inputs": [
        {
          "type": "&base64::display::Base64Display<'a, 'e, E>",
          "name": "self",
          "mode": "&"
        }
      ],
      "generic_params": [
        "T"
      ]
    },
    {
      "id": "T44",
      "name": "borrow_mut",
      "kind": "method",
      "inputs": [
        {
          "type": "&mut base64::display::Base64Display<'a, 'e, E>",
          "name": "self",
          "mode": "&mut"
        }
      ],
      "generic_params": [
        "T"
      ]
    },
    {
      "id": "T45",
      "name": "into",
      "kind": "method",
      "inputs": [
        {
          "type": "base64::display::Base64Display<'a, 'e, E>",
          "name": "self",
          "mode": "value"
        }
      ],
      "generic_params": [
        "T",
        "U"
      ]
    },
    {
      "id": "T46",
      "name": "from",
      "kind": "method",
      "generic_params": [
        "T"
      ]
    },
    {
      "id": "T47",
      "name": "try_into",
      "kind": "method",
      "inputs": [
        {
          "type": "base64::display::Base64Display<'a, 'e, E>",
          "name": "self",
          "mode": "value"
        }
      ],
      "outputs": [
        {
          "type": "Error>",
          "mode": "value"
        }
      ],
      "generic_params": [
        "T",
        "U"
      ]
    },
    {
      "id": "T48",
      "name": "try_from",
      "kind": "method",
      "outputs": [
        {
          "type": "Error>",
          "mode": "value"
        }
      ],
      "generic_params": [
        "T",
        "U"
      ]
    },
    {
      "id": "T49",
      "name": "type_id",
      "kind": "method",
      "inputs": [
        {
          "type": "&base64::display::Base64Display<'a, 'e, E>",
          "name": "self",
          "mode": "&"
        }
      ],
      "outputs": [
        {
          "type": "TypeId",
          "mode": "value"
        }
      ],
      "generic_params": [
        "T"
      ]
    },
    {
      "id": "T50",
      "name": "to_string",
      "kind": "method",
      "inputs": [
        {
          "type": "&base64::display::Base64Display<'a, 'e, E>",
          "name": "self",
          "mode": "&"
        }
      ],
      "outputs": [
        {
          "type": "String",
          "mode": "value"
        }
      ],
      "generic_params": [
        "T"
      ]
    },
    {
      "id": "T51",
      "name": "fmt",
      "kind": "method",
      "inputs": [
        {
          "type": "&mut Formatter<'_>",
          "name": "formatter",
          "mode": "&mut"
        },
        {
          "type": "&base64::display::Base64Display<'a, 'e, E>",
          "name": "self",
          "mode": "&"
        }
      ],
      "outputs": [
        {
          "type": "Error>",
          "mode": "value"
        }
      ],
      "generic_params": [
        "''a",
        "''e",
        "E: Engine"
      ]
    },
    {
      "id": "T52",
      "name": "borrow",
      "kind": "method",
      "inputs": [
        {
          "type": "&base64::decode::DecodeSliceError",
          "name": "self",
          "mode": "&"
        }
      ],
      "generic_params": [
        "T"
      ]
    },
    {
      "id": "T53",
      "name": "borrow_mut",
      "kind": "method",
      "inputs": [
        {
          "type": "&mut base64::decode::DecodeSliceError",
          "name": "self",
          "mode": "&mut"
        }
      ],
      "generic_params": [
        "T"
      ]
    },
    {
      "id": "T54",
      "name": "clone_to_uninit",
      "kind": "method",
      "inputs": [
        {
          "type": "*mut u8",
          "name": "dest",
          "mode": "*mut"
        },
        {
          "type": "&base64::decode::DecodeSliceError",
          "name": "self",
          "mode": "&"
        }
      ],
      "generic_params": [
        "T"
      ]
    },
    {
      "id": "T55",
      "name": "into",
      "kind": "method",
      "inputs": [
        {
          "type": "base64::decode::DecodeSliceError",
          "name": "self",
          "mode": "value"
        }
      ],
      "outputs": [
        {
          "type": "U",
          "mode": "value"
        }
      ],
      "generic_params": [
        "T",
        "U"
      ]
    },
    {
      "id": "T56",
      "name": "from",
      "kind": "method",
      "inputs": [
        {
          "type": "T",
          "name": "t",
          "mode": "value"
        }
      ],
      "outputs": [
        {
          "type": "T",
          "mode": "value"
        }
      ],
      "generic_params": [
        "T"
      ]
    },
    {
      "id": "T57",
      "name": "try_into",
      "kind": "method",
      "inputs": [
        {
          "type": "base64::decode::DecodeSliceError",
          "name": "self",
          "mode": "value"
        }
      ],
      "outputs": [
        {
          "type": "Error>",
          "mode": "value"
        }
      ],
      "generic_params": [
        "T",
        "U"
      ]
    },
    {
      "id": "T58",
      "name": "try_from",
      "kind": "method",
      "inputs": [
        {
          "type": "U",
          "name": "value",
          "mode": "value"
        }
      ],
      "outputs": [
        {
          "type": "Error>",
          "mode": "value"
        }
      ],
      "generic_params": [
        "T",
        "U"
      ]
    },
    {
      "id": "T59",
      "name": "type_id",
      "kind": "method",
      "inputs": [
        {
          "type": "&base64::decode::DecodeSliceError",
          "name": "self",
          "mode": "&"
        }
      ],
      "outputs": [
        {
          "type": "TypeId",
          "mode": "value"
        }
      ],
      "generic_params": [
        "T"
      ]
    },
    {
      "id": "T60",
      "name": "to_owned",
      "kind": "method",
      "inputs": [
        {
          "type": "&base64::decode::DecodeSliceError",
          "name": "self",
          "mode": "&"
        }
      ],
      "outputs": [
        {
          "type": "T",
          "mode": "value"
        }
      ],
      "generic_params": [
        "T"
      ]
    },
    {
      "id": "T61",
      "name": "clone_into",
      "kind": "method",
      "inputs": [
        {
          "type": "&base64::decode::DecodeSliceError",
          "name": "self",
          "mode": "&"
        }
      ],
      "generic_params": [
        "T"
      ]
    },
    {
      "id": "T62",
      "name": "to_string",
      "kind": "method",
      "inputs": [
        {
          "type": "&base64::decode::DecodeSliceError",
          "name": "self",
          "mode": "&"
        }
      ],
      "outputs": [
        {
          "type": "String",
          "mode": "value"
        }
      ],
      "generic_params": [
        "T"
      ]
    },
    {
      "id": "T63",
      "name": "clone",
      "kind": "method",
      "inputs": [
        {
          "type": "&base64::decode::DecodeSliceError",
          "name": "self",
          "mode": "&"
        }
      ],
      "outputs": [
        {
          "type": "DecodeSliceError",
          "mode": "value"
        }
      ]
    },
    {
      "id": "T64",
      "name": "fmt",
      "kind": "method",
      "inputs": [
        {
          "type": "&mut $crate::fmt::Formatter<'_>",
          "name": "f",
          "mode": "&mut"
        },
        {
          "type": "&base64::decode::DecodeSliceError",
          "name": "self",
          "mode": "&"
        }
      ],
      "outputs": [
        {
          "type": "Result",
          "mode": "value"
        }
      ]
    },
    {
      "id": "T65",
      "name": "eq",
      "kind": "method",
      "inputs": [
        {
          "type": "&DecodeSliceError",
          "name": "other",
          "mode": "&"
        },
        {
          "type": "&base64::decode::DecodeSliceError",
          "name": "self",
          "mode": "&"
        }
      ],
      "outputs": [
        {
          "type": "bool",
          "mode": "value"
        }
      ]
    },
    {
      "id": "T66",
      "name": "fmt",
      "kind": "method",
      "inputs": [
        {
          "type": "&mut fmt::Formatter<'_>",
          "name": "f",
          "mode": "&mut"
        },
        {
          "type": "&base64::decode::DecodeSliceError",
          "name": "self",
          "mode": "&"
        }
      ],
      "outputs": [
        {
          "type": "Result",
          "mode": "value"
        }
      ]
    },
    {
      "id": "T67",
      "name": "source",
      "kind": "method",
      "inputs": [
        {
          "type": "&base64::decode::DecodeSliceError",
          "name": "self",
          "mode": "&"
        }
      ],
      "outputs": [
        {
          "type": "Error + 'static)>",
          "mode": "value"
        }
      ]
    },
    {
      "id": "T68",
      "name": "from",
      "kind": "method",
      "inputs": [
        {
          "type": "DecodeError",
          "name": "e",
          "mode": "value"
        }
      ],
      "outputs": [
        {
          "type": "DecodeSliceError",
          "mode": "value"
        }
      ]
    },
    {
      "id": "T69",
      "name": "new",
      "kind": "method",
      "outputs": [
        {
          "type": "GeneralPurposeConfig",
          "mode": "value"
        }
      ]
    },
    {
      "id": "T70",
      "name": "with_encode_padding",
      "kind": "method",
      "inputs": [
        {
          "type": "bool",
          "name": "padding",
          "mode": "value"
        },
        {
          "type": "base64::engine::general_purpose::GeneralPurposeConfig",
          "name": "self",
          "mode": "value"
        }
      ],
      "outputs": [
        {
          "type": "GeneralPurposeConfig",
          "mode": "value"
        }
      ]
    },
    {
      "id": "T71",
      "name": "with_decode_allow_trailing_bits",
      "kind": "method",
      "inputs": [
        {
          "type": "bool",
          "name": "allow",
          "mode": "value"
        },
        {
          "type": "base64::engine::general_purpose::GeneralPurposeConfig",
          "name": "self",
          "mode": "value"
        }
      ],
      "outputs": [
        {
          "type": "GeneralPurposeConfig",
          "mode": "value"
        }
      ]
    },
    {
      "id": "T72",
      "name": "with_decode_padding_mode",
      "kind": "method",
      "inputs": [
        {
          "type": "DecodePaddingMode",
          "name": "mode",
          "mode": "value"
        },
        {
          "type": "base64::engine::general_purpose::GeneralPurposeConfig",
          "name": "self",
          "mode": "value"
        }
      ],
      "outputs": [
        {
          "type": "GeneralPurposeConfig",
          "mode": "value"
        }
      ]
    },
    {
      "id": "T73",
      "name": "borrow",
      "kind": "method",
      "inputs": [
        {
          "type": "&base64::engine::general_purpose::GeneralPurposeConfig",
          "name": "self",
          "mode": "&"
        }
      ],
      "generic_params": [
        "T"
      ]
    },
    {
      "id": "T74",
      "name": "borrow_mut",
      "kind": "method",
      "inputs": [
        {
          "type": "&mut base64::engine::general_purpose::GeneralPurposeConfig",
          "name": "self",
          "mode": "&mut"
        }
      ],
      "generic_params": [
        "T"
      ]
    },
    {
      "id": "T75",
      "name": "clone_to_uninit",
      "kind": "method",
      "inputs": [
        {
          "type": "*mut u8",
          "name": "dest",
          "mode": "*mut"
        },
        {
          "type": "&base64::engine::general_purpose::GeneralPurposeConfig",
          "name": "self",
          "mode": "&"
        }
      ],
      "generic_params": [
        "T"
      ]
    },
    {
      "id": "T76",
      "name": "into",
      "kind": "method",
      "inputs": [
        {
          "type": "base64::engine::general_purpose::GeneralPurposeConfig",
          "name": "self",
          "mode": "value"
        }
      ],
      "outputs": [
        {
          "type": "U",
          "mode": "value"
        }
      ],
      "generic_params": [
        "T",
        "U"
      ]
    },
    {
      "id": "T77",
      "name": "from",
      "kind": "method",
      "inputs": [
        {
          "type": "T",
          "name": "t",
          "mode": "value"
        }
      ],
      "outputs": [
        {
          "type": "T",
          "mode": "value"
        }
      ],
      "generic_params": [
        "T"
      ]
    },
    {
      "id": "T78",
      "name": "try_into",
      "kind": "method",
      "inputs": [
        {
          "type": "base64::engine::general_purpose::GeneralPurposeConfig",
          "name": "self",
          "mode": "value"
        }
      ],
      "outputs": [
        {
          "type": "Error>",
          "mode": "value"
        }
      ],
      "generic_params": [
        "T",
        "U"
      ]
    },
    {
      "id": "T79",
      "name": "try_from",
      "kind": "method",
      "inputs": [
        {
          "type": "U",
          "name": "value",
          "mode": "value"
        }
      ],
      "outputs": [
        {
          "type": "Error>",
          "mode": "value"
        }
      ],
      "generic_params": [
        "T",
        "U"
      ]
    },
    {
      "id": "T80",
      "name": "type_id",
      "kind": "method",
      "inputs": [
        {
          "type": "&base64::engine::general_purpose::GeneralPurposeConfig",
          "name": "self",
          "mode": "&"
        }
      ],
      "outputs": [
        {
          "type": "TypeId",
          "mode": "value"
        }
      ],
      "generic_params": [
        "T"
      ]
    },
    {
      "id": "T81",
      "name": "to_owned",
      "kind": "method",
      "inputs": [
        {
          "type": "&base64::engine::general_purpose::GeneralPurposeConfig",
          "name": "self",
          "mode": "&"
        }
      ],
      "outputs": [
        {
          "type": "T",
          "mode": "value"
        }
      ],
      "generic_params": [
        "T"
      ]
    },
    {
      "id": "T82",
      "name": "clone_into",
      "kind": "method",
      "inputs": [
        {
          "type": "&base64::engine::general_purpose::GeneralPurposeConfig",
          "name": "self",
          "mode": "&"
        }
      ],
      "generic_params": [
        "T"
      ]
    },
    {
      "id": "T83",
      "name": "clone",
      "kind": "method",
      "inputs": [
        {
          "type": "&base64::engine::general_purpose::GeneralPurposeConfig",
          "name": "self",
          "mode": "&"
        }
      ],
      "outputs": [
        {
          "type": "GeneralPurposeConfig",
          "mode": "value"
        }
      ]
    },
    {
      "id": "T84",
      "name": "fmt",
      "kind": "method",
      "inputs": [
        {
          "type": "&mut $crate::fmt::Formatter<'_>",
          "name": "f",
          "mode": "&mut"
        },
        {
          "type": "&base64::engine::general_purpose::GeneralPurposeConfig",
          "name": "self",
          "mode": "&"
        }
      ],
      "outputs": [
        {
          "type": "Result",
          "mode": "value"
        }
      ]
    },
    {
      "id": "T85",
      "name": "default",
      "kind": "method",
      "outputs": [
        {
          "type": "GeneralPurposeConfig",
          "mode": "value"
        }
      ]
    },
    {
      "id": "T86",
      "name": "encode_padding",
      "kind": "method",
      "inputs": [
        {
          "type": "&base64::engine::general_purpose::GeneralPurposeConfig",
          "name": "self",
          "mode": "&"
        }
      ],
      "outputs": [
        {
          "type": "bool",
          "mode": "value"
        }
      ]
    },
    {
      "id": "T87",
      "name": "borrow",
      "kind": "method",
      "inputs": [
        {
          "type": "&base64::engine::DecodePaddingMode",
          "name": "self",
          "mode": "&"
        }
      ],
      "generic_params": [
        "T"
      ]
    },
    {
      "id": "T88",
      "name": "borrow_mut",
      "kind": "method",
      "inputs": [
        {
          "type": "&mut base64::engine::DecodePaddingMode",
          "name": "self",
          "mode": "&mut"
        }
      ],
      "generic_params": [
        "T"
      ]
    },
    {
      "id": "T89",
      "name": "clone_to_uninit",
      "kind": "method",
      "inputs": [
        {
          "type": "*mut u8",
          "name": "dest",
          "mode": "*mut"
        },
        {
          "type": "&base64::engine::DecodePaddingMode",
          "name": "self",
          "mode": "&"
        }
      ],
      "generic_params": [
        "T"
      ]
    },
    {
      "id": "T90",
      "name": "into",
      "kind": "method",
      "inputs": [
        {
          "type": "base64::engine::DecodePaddingMode",
          "name": "self",
          "mode": "value"
        }
      ],
      "outputs": [
        {
          "type": "U",
          "mode": "value"
        }
      ],
      "generic_params": [
        "T",
        "U"
      ]
    },
    {
      "id": "T91",
      "name": "from",
      "kind": "method",
      "inputs": [
        {
          "type": "T",
          "name": "t",
          "mode": "value"
        }
      ],
      "outputs": [
        {
          "type": "T",
          "mode": "value"
        }
      ],
      "generic_params": [
        "T"
      ]
    },
    {
      "id": "T92",
      "name": "try_into",
      "kind": "method",
      "inputs": [
        {
          "type": "base64::engine::DecodePaddingMode",
          "name": "self",
          "mode": "value"
        }
      ],
      "outputs": [
        {
          "type": "Error>",
          "mode": "value"
        }
      ],
      "generic_params": [
        "T",
        "U"
      ]
    },
    {
      "id": "T93",
      "name": "try_from",
      "kind": "method",
      "inputs": [
        {
          "type": "U",
          "name": "value",
          "mode": "value"
        }
      ],
      "outputs": [
        {
          "type": "Error>",
          "mode": "value"
        }
      ],
      "generic_params": [
        "T",
        "U"
      ]
    },
    {
      "id": "T94",
      "name": "type_id",
      "kind": "method",
      "inputs": [
        {
          "type": "&base64::engine::DecodePaddingMode",
          "name": "self",
          "mode": "&"
        }
      ],
      "outputs": [
        {
          "type": "TypeId",
          "mode": "value"
        }
      ],
      "generic_params": [
        "T"
      ]
    },
    {
      "id": "T95",
      "name": "to_owned",
      "kind": "method",
      "inputs": [
        {
          "type": "&base64::engine::DecodePaddingMode",
          "name": "self",
          "mode": "&"
        }
      ],
      "outputs": [
        {
          "type": "T",
          "mode": "value"
        }
      ],
      "generic_params": [
        "T"
      ]
    },
    {
      "id": "T96",
      "name": "clone_into",
      "kind": "method",
      "inputs": [
        {
          "type": "&base64::engine::DecodePaddingMode",
          "name": "self",
          "mode": "&"
        }
      ],
      "generic_params": [
        "T"
      ]
    },
    {
      "id": "T97",
      "name": "clone",
      "kind": "method",
      "inputs": [
        {
          "type": "&base64::engine::DecodePaddingMode",
          "name": "self",
          "mode": "&"
        }
      ],
      "outputs": [
        {
          "type": "DecodePaddingMode",
          "mode": "value"
        }
      ]
    },
    {
      "id": "T98",
      "name": "fmt",
      "kind": "method",
      "inputs": [
        {
          "type": "&mut $crate::fmt::Formatter<'_>",
          "name": "f",
          "mode": "&mut"
        },
        {
          "type": "&base64::engine::DecodePaddingMode",
          "name": "self",
          "mode": "&"
        }
      ],
      "outputs": [
        {
          "type": "Result",
          "mode": "value"
        }
      ]
    },
    {
      "id": "T99",
      "name": "eq",
      "kind": "method",
      "inputs": [
        {
          "type": "&DecodePaddingMode",
          "name": "other",
          "mode": "&"
        },
        {
          "type": "&base64::engine::DecodePaddingMode",
          "name": "self",
          "mode": "&"
        }
      ],
      "outputs": [
        {
          "type": "bool",
          "mode": "value"
        }
      ]
    },
    {
      "id": "T100",
      "name": "new",
      "kind": "method",
      "inputs": [
        {
          "type": "&str",
          "name": "alphabet",
          "mode": "&"
        }
      ],
      "outputs": [
        {
          "type": "Alphabet, ParseAlphabetError>",
          "mode": "value"
        }
      ]
    },
    {
      "id": "T101",
      "name": "as_str",
      "kind": "method",
      "inputs": [
        {
          "type": "&base64::alphabet::Alphabet",
          "name": "self",
          "mode": "&"
        }
      ],
      "outputs": [
        {
          "type": "str",
          "mode": "&"
        }
      ]
    },
    {
      "id": "T102",
      "name": "borrow",
      "kind": "method",
      "inputs": [
        {
          "type": "&base64::alphabet::Alphabet",
          "name": "self",
          "mode": "&"
        }
      ],
      "generic_params": [
        "T"
      ]
    },
    {
      "id": "T103",
      "name": "borrow_mut",
      "kind": "method",
      "inputs": [
        {
          "type": "&mut base64::alphabet::Alphabet",
          "name": "self",
          "mode": "&mut"
        }
      ],
      "generic_params": [
        "T"
      ]
    },
    {
      "id": "T104",
      "name": "clone_to_uninit",
      "kind": "method",
      "inputs": [
        {
          "type": "*mut u8",
          "name": "dest",
          "mode": "*mut"
        },
        {
          "type": "&base64::alphabet::Alphabet",
          "name": "self",
          "mode": "&"
        }
      ],
      "generic_params": [
        "T"
      ]
    },
    {
      "id": "T105",
      "name": "into",
      "kind": "method",
      "inputs": [
        {
          "type": "base64::alphabet::Alphabet",
          "name": "self",
          "mode": "value"
        }
      ],
      "outputs": [
        {
          "type": "U",
          "mode": "value"
        }
      ],
      "generic_params": [
        "T",
        "U"
      ]
    },
    {
      "id": "T106",
      "name": "from",
      "kind": "method",
      "inputs": [
        {
          "type": "T",
          "name": "t",
          "mode": "value"
        }
      ],
      "outputs": [
        {
          "type": "T",
          "mode": "value"
        }
      ],
      "generic_params": [
        "T"
      ]
    },
    {
      "id": "T107",
      "name": "try_into",
      "kind": "method",
      "inputs": [
        {
          "type": "base64::alphabet::Alphabet",
          "name": "self",
          "mode": "value"
        }
      ],
      "outputs": [
        {
          "type": "Error>",
          "mode": "value"
        }
      ],
      "generic_params": [
        "T",
        "U"
      ]
    },
    {
      "id": "T108",
      "name": "try_from",
      "kind": "method",
      "inputs": [
        {
          "type": "U",
          "name": "value",
          "mode": "value"
        }
      ],
      "outputs": [
        {
          "type": "Error>",
          "mode": "value"
        }
      ],
      "generic_params": [
        "T",
        "U"
      ]
    },
    {
      "id": "T109",
      "name": "type_id",
      "kind": "method",
      "inputs": [
        {
          "type": "&base64::alphabet::Alphabet",
          "name": "self",
          "mode": "&"
        }
      ],
      "outputs": [
        {
          "type": "TypeId",
          "mode": "value"
        }
      ],
      "generic_params": [
        "T"
      ]
    },
    {
      "id": "T110",
      "name": "to_owned",
      "kind": "method",
      "inputs": [
        {
          "type": "&base64::alphabet::Alphabet",
          "name": "self",
          "mode": "&"
        }
      ],
      "outputs": [
        {
          "type": "T",
          "mode": "value"
        }
      ],
      "generic_params": [
        "T"
      ]
    },
    {
      "id": "T111",
      "name": "clone_into",
      "kind": "method",
      "inputs": [
        {
          "type": "&base64::alphabet::Alphabet",
          "name": "self",
          "mode": "&"
        }
      ],
      "generic_params": [
        "T"
      ]
    },
    {
      "id": "T112",
      "name": "clone",
      "kind": "method",
      "inputs": [
        {
          "type": "&base64::alphabet::Alphabet",
          "name": "self",
          "mode": "&"
        }
      ],
      "outputs": [
        {
          "type": "Alphabet",
          "mode": "value"
        }
      ]
    },
    {
      "id": "T113",
      "name": "fmt",
      "kind": "method",
      "inputs": [
        {
          "type": "&mut $crate::fmt::Formatter<'_>",
          "name": "f",
          "mode": "&mut"
        },
        {
          "type": "&base64::alphabet::Alphabet",
          "name": "self",
          "mode": "&"
        }
      ],
      "outputs": [
        {
          "type": "Result",
          "mode": "value"
        }
      ]
    },
    {
      "id": "T114",
      "name": "eq",
      "kind": "method",
      "inputs": [
        {
          "type": "&Alphabet",
          "name": "other",
          "mode": "&"
        },
        {
          "type": "&base64::alphabet::Alphabet",
          "name": "self",
          "mode": "&"
        }
      ],
      "outputs": [
        {
          "type": "bool",
          "mode": "value"
        }
      ]
    },
    {
      "id": "T115",
      "name": "try_from",
      "kind": "method",
      "inputs": [
        {
          "type": "&str",
          "name": "value",
          "mode": "&"
        }
      ],
      "outputs": [
        {
          "type": "Error>",
          "mode": "value"
        }
      ]
    },
    {
      "id": "T116",
      "name": "new",
      "kind": "method",
      "outputs": [
        {
          "type": "DecoderReader",
          "mode": "value"
        }
      ],
      "generic_params": [
        "''e",
        "E: Engine",
        "R: io::Read"
      ]
    },
    {
      "id": "T117",
      "name": "into_inner",
      "kind": "method",
      "inputs": [
        {
          "type": "base64::read::decoder::DecoderReader<'e, E, R>",
          "name": "self",
          "mode": "value"
        }
      ],
      "generic_params": [
        "''e",
        "E: Engine",
        "R: io::Read"
      ]
    },
    {
      "id": "T118",
      "name": "borrow",
      "kind": "method",
      "inputs": [
        {
          "type": "&base64::read::decoder::DecoderReader<'e, E, R>",
          "name": "self",
          "mode": "&"
        }
      ],
      "generic_params": [
        "T"
      ]
    },
    {
      "id": "T119",
      "name": "borrow_mut",
      "kind": "method",
      "inputs": [
        {
          "type": "&mut base64::read::decoder::DecoderReader<'e, E, R>",
          "name": "self",
          "mode": "&mut"
        }
      ],
      "generic_params": [
        "T"
      ]
    },
    {
      "id": "T120",
      "name": "into",
      "kind": "method",
      "inputs": [
        {
          "type": "base64::read::decoder::DecoderReader<'e, E, R>",
          "name": "self",
          "mode": "value"
        }
      ],
      "generic_params": [
        "T",
        "U"
      ]
    },
    {
      "id": "T121",
      "name": "from",
      "kind": "method",
      "generic_params": [
        "T"
      ]
    },
    {
      "id": "T122",
      "name": "try_into",
      "kind": "method",
      "inputs": [
        {
          "type": "base64::read::decoder::DecoderReader<'e, E, R>",
          "name": "self",
          "mode": "value"
        }
      ],
      "outputs": [
        {
          "type": "Error>",
          "mode": "value"
        }
      ],
      "generic_params": [
        "T",
        "U"
      ]
    },
    {
      "id": "T123",
      "name": "try_from",
      "kind": "method",
      "outputs": [
        {
          "type": "Error>",
          "mode": "value"
        }
      ],
      "generic_params": [
        "T",
        "U"
      ]
    },
    {
      "id": "T124",
      "name": "type_id",
      "kind": "method",
      "inputs": [
        {
          "type": "&base64::read::decoder::DecoderReader<'e, E, R>",
          "name": "self",
          "mode": "&"
        }
      ],
      "outputs": [
        {
          "type": "TypeId",
          "mode": "value"
        }
      ],
      "generic_params": [
        "T"
      ]
    },
    {
      "id": "T125",
      "name": "fmt",
      "kind": "method",
      "inputs": [
        {
          "type": "&mut fmt::Formatter<'_>",
          "name": "f",
          "mode": "&mut"
        },
        {
          "type": "&base64::read::decoder::DecoderReader<'e, E, R>",
          "name": "self",
          "mode": "&"
        }
      ],
      "outputs": [
        {
          "type": "Result",
          "mode": "value"
        }
      ],
      "generic_params": [
        "''e",
        "E: Engine",
        "R: io::Read"
      ]
    },
    {
      "id": "T126",
      "name": "read",
      "kind": "method",
      "inputs": [
        {
          "type": "&mut [u8]",
          "name": "buf",
          "mode": "&mut"
        },
        {
          "type": "&mut base64::read::decoder::DecoderReader<'e, E, R>",
          "name": "self",
          "mode": "&mut"
        }
      ],
      "outputs": [
        {
          "type": "Result",
          "mode": "value"
        }
      ],
      "generic_params": [
        "''e",
        "E: Engine",
        "R: io::Read"
      ]
    },
    {
      "id": "T127",
      "name": "from_consumer",
      "kind": "method",
      "outputs": [
        {
          "type": "EncoderStringWriter",
          "mode": "value"
        }
      ],
      "generic_params": [
        "''e",
        "E: Engine",
        "S: StrConsumer"
      ]
    },
    {
      "id": "T128",
      "name": "into_inner",
      "kind": "method",
      "inputs": [
        {
          "type": "base64::write::encoder_string_writer::EncoderStringWriter<'e, E, S>",
          "name": "self",
          "mode": "value"
        }
      ],
      "generic_params": [
        "''e",
        "E: Engine",
        "S: StrConsumer"
      ]
    },
    {
      "id": "T129",
      "name": "new",
      "kind": "method",
      "outputs": [
        {
          "type": "EncoderStringWriter",
          "mode": "value"
        }
      ],
      "generic_params": [
        "''e",
        "E: Engine"
      ]
    },
    {
      "id": "T130",
      "name": "borrow",
      "kind": "method",
      "inputs": [
        {
          "type": "&base64::write::encoder_string_writer::EncoderStringWriter<'e, E, S>",
          "name": "self",
          "mode": "&"
        }
      ],
      "generic_params": [
        "T"
      ]
    },
    {
      "id": "T131",
      "name": "borrow_mut",
      "kind": "method",
      "inputs": [
        {
          "type": "&mut base64::write::encoder_string_writer::EncoderStringWriter<'e, E, S>",
          "name": "self",
          "mode": "&mut"
        }
      ],
      "generic_params": [
        "T"
      ]
    },
    {
      "id": "T132",
      "name": "into",
      "kind": "method",
      "inputs": [
        {
          "type": "base64::write::encoder_string_writer::EncoderStringWriter<'e, E, S>",
          "name": "self",
          "mode": "value"
        }
      ],
      "generic_params": [
        "T",
        "U"
      ]
    },
    {
      "id": "T133",
      "name": "from",
      "kind": "method",
      "generic_params": [
        "T"
      ]
    },
    {
      "id": "T134",
      "name": "try_into",
      "kind": "method",
      "inputs": [
        {
          "type": "base64::write::encoder_string_writer::EncoderStringWriter<'e, E, S>",
          "name": "self",
          "mode": "value"
        }
      ],
      "outputs": [
        {
          "type": "Error>",
          "mode": "value"
        }
      ],
      "generic_params": [
        "T",
        "U"
      ]
    },
    {
      "id": "T135",
      "name": "try_from",
      "kind": "method",
      "outputs": [
        {
          "type": "Error>",
          "mode": "value"
        }
      ],
      "generic_params": [
        "T",
        "U"
      ]
    },
    {
      "id": "T136",
      "name": "type_id",
      "kind": "method",
      "inputs": [
        {
          "type": "&base64::write::encoder_string_writer::EncoderStringWriter<'e, E, S>",
          "name": "self",
          "mode": "&"
        }
      ],
      "outputs": [
        {
          "type": "TypeId",
          "mode": "value"
        }
      ],
      "generic_params": [
        "T"
      ]
    },
    {
      "id": "T137",
      "name": "write",
      "kind": "method",
      "inputs": [
        {
          "type": "&[u8]",
          "name": "buf",
          "mode": "&"
        },
        {
          "type": "&mut base64::write::encoder_string_writer::EncoderStringWriter<'e, E, S>",
          "name": "self",
          "mode": "&mut"
        }
      ],
      "outputs": [
        {
          "type": "Result",
          "mode": "value"
        }
      ],
      "generic_params": [
        "''e",
        "E: Engine",
        "S: StrConsumer"
      ]
    },
    {
      "id": "T138",
      "name": "flush",
      "kind": "method",
      "inputs": [
        {
          "type": "&mut base64::write::encoder_string_writer::EncoderStringWriter<'e, E, S>",
          "name": "self",
          "mode": "&mut"
        }
      ],
      "outputs": [
        {
          "type": "Result",
          "mode": "value"
        }
      ],
      "generic_params": [
        "''e",
        "E: Engine",
        "S: StrConsumer"
      ]
    },
    {
      "id": "T139",
      "name": "borrow",
      "kind": "method",
      "inputs": [
        {
          "type": "&base64::engine::DecodeMetadata",
          "name": "self",
          "mode": "&"
        }
      ],
      "generic_params": [
        "T"
      ]
    },
    {
      "id": "T140",
      "name": "borrow_mut",
      "kind": "method",
      "inputs": [
        {
          "type": "&mut base64::engine::DecodeMetadata",
          "name": "self",
          "mode": "&mut"
        }
      ],
      "generic_params": [
        "T"
      ]
    },
    {
      "id": "T141",
      "name": "into",
      "kind": "method",
      "inputs": [
        {
          "type": "base64::engine::DecodeMetadata",
          "name": "self",
          "mode": "value"
        }
      ],
      "outputs": [
        {
          "type": "U",
          "mode": "value"
        }
      ],
      "generic_params": [
        "T",
        "U"
      ]
    },
    {
      "id": "T142",
      "name": "from",
      "kind": "method",
      "inputs": [
        {
          "type": "T",
          "name": "t",
          "mode": "value"
        }
      ],
      "outputs": [
        {
          "type": "T",
          "mode": "value"
        }
      ],
      "generic_params": [
        "T"
      ]
    },
    {
      "id": "T143",
      "name": "try_into",
      "kind": "method",
      "inputs": [
        {
          "type": "base64::engine::DecodeMetadata",
          "name": "self",
          "mode": "value"
        }
      ],
      "outputs": [
        {
          "type": "Error>",
          "mode": "value"
        }
      ],
      "generic_params": [
        "T",
        "U"
      ]
    },
    {
      "id": "T144",
      "name": "try_from",
      "kind": "method",
      "inputs": [
        {
          "type": "U",
          "name": "value",
          "mode": "value"
        }
      ],
      "outputs": [
        {
          "type": "Error>",
          "mode": "value"
        }
      ],
      "generic_params": [
        "T",
        "U"
      ]
    },
    {
      "id": "T145",
      "name": "type_id",
      "kind": "method",
      "inputs": [
        {
          "type": "&base64::engine::DecodeMetadata",
          "name": "self",
          "mode": "&"
        }
      ],
      "outputs": [
        {
          "type": "TypeId",
          "mode": "value"
        }
      ],
      "generic_params": [
        "T"
      ]
    },
    {
      "id": "T146",
      "name": "eq",
      "kind": "method",
      "inputs": [
        {
          "type": "&DecodeMetadata",
          "name": "other",
          "mode": "&"
        },
        {
          "type": "&base64::engine::DecodeMetadata",
          "name": "self",
          "mode": "&"
        }
      ],
      "outputs": [
        {
          "type": "bool",
          "mode": "value"
        }
      ]
    },
    {
      "id": "T147",
      "name": "fmt",
      "kind": "method",
      "inputs": [
        {
          "type": "&mut $crate::fmt::Formatter<'_>",
          "name": "f",
          "mode": "&mut"
        },
        {
          "type": "&base64::engine::DecodeMetadata",
          "name": "self",
          "mode": "&"
        }
      ],
      "outputs": [
        {
          "type": "Result",
          "mode": "value"
        }
      ]
    },
    {
      "id": "T148",
      "name": "new",
      "kind": "method",
      "inputs": [
        {
          "type": "GeneralPurposeConfig",
          "name": "config",
          "mode": "value"
        },
        {
          "type": "&Alphabet",
          "name": "alphabet",
          "mode": "&"
        }
      ],
      "outputs": [
        {
          "type": "GeneralPurpose",
          "mode": "value"
        }
      ]
    },
    {
      "id": "T149",
      "name": "borrow",
      "kind": "method",
      "inputs": [
        {
          "type": "&base64::engine::general_purpose::GeneralPurpose",
          "name": "self",
          "mode": "&"
        }
      ],
      "generic_params": [
        "T"
      ]
    },
    {
      "id": "T150",
      "name": "borrow_mut",
      "kind": "method",
      "inputs": [
        {
          "type": "&mut base64::engine::general_purpose::GeneralPurpose",
          "name": "self",
          "mode": "&mut"
        }
      ],
      "generic_params": [
        "T"
      ]
    },
    {
      "id": "T151",
      "name": "clone_to_uninit",
      "kind": "method",
      "inputs": [
        {
          "type": "*mut u8",
          "name": "dest",
          "mode": "*mut"
        },
        {
          "type": "&base64::engine::general_purpose::GeneralPurpose",
          "name": "self",
          "mode": "&"
        }
      ],
      "generic_params": [
        "T"
      ]
    },
    {
      "id": "T152",
      "name": "into",
      "kind": "method",
      "inputs": [
        {
          "type": "base64::engine::general_purpose::GeneralPurpose",
          "name": "self",
          "mode": "value"
        }
      ],
      "outputs": [
        {
          "type": "U",
          "mode": "value"
        }
      ],
      "generic_params": [
        "T",
        "U"
      ]
    },
    {
      "id": "T153",
      "name": "from",
      "kind": "method",
      "inputs": [
        {
          "type": "T",
          "name": "t",
          "mode": "value"
        }
      ],
      "outputs": [
        {
          "type": "T",
          "mode": "value"
        }
      ],
      "generic_params": [
        "T"
      ]
    },
    {
      "id": "T154",
      "name": "try_into",
      "kind": "method",
      "inputs": [
        {
          "type": "base64::engine::general_purpose::GeneralPurpose",
          "name": "self",
          "mode": "value"
        }
      ],
      "outputs": [
        {
          "type": "Error>",
          "mode": "value"
        }
      ],
      "generic_params": [
        "T",
        "U"
      ]
    },
    {
      "id": "T155",
      "name": "try_from",
      "kind": "method",
      "inputs": [
        {
          "type": "U",
          "name": "value",
          "mode": "value"
        }
      ],
      "outputs": [
        {
          "type": "Error>",
          "mode": "value"
        }
      ],
      "generic_params": [
        "T",
        "U"
      ]
    },
    {
      "id": "T156",
      "name": "type_id",
      "kind": "method",
      "inputs": [
        {
          "type": "&base64::engine::general_purpose::GeneralPurpose",
          "name": "self",
          "mode": "&"
        }
      ],
      "outputs": [
        {
          "type": "TypeId",
          "mode": "value"
        }
      ],
      "generic_params": [
        "T"
      ]
    },
    {
      "id": "T157",
      "name": "to_owned",
      "kind": "method",
      "inputs": [
        {
          "type": "&base64::engine::general_purpose::GeneralPurpose",
          "name": "self",
          "mode": "&"
        }
      ],
      "outputs": [
        {
          "type": "T",
          "mode": "value"
        }
      ],
      "generic_params": [
        "T"
      ]
    },
    {
      "id": "T158",
      "name": "clone_into",
      "kind": "method",
      "inputs": [
        {
          "type": "&base64::engine::general_purpose::GeneralPurpose",
          "name": "self",
          "mode": "&"
        }
      ],
      "generic_params": [
        "T"
      ]
    },
    {
      "id": "T159",
      "name": "fmt",
      "kind": "method",
      "inputs": [
        {
          "type": "&mut $crate::fmt::Formatter<'_>",
          "name": "f",
          "mode": "&mut"
        },
        {
          "type": "&base64::engine::general_purpose::GeneralPurpose",
          "name": "self",
          "mode": "&"
        }
      ],
      "outputs": [
        {
          "type": "Result",
          "mode": "value"
        }
      ]
    },
    {
      "id": "T160",
      "name": "clone",
      "kind": "method",
      "inputs": [
        {
          "type": "&base64::engine::general_purpose::GeneralPurpose",
          "name": "self",
          "mode": "&"
        }
      ],
      "outputs": [
        {
          "type": "GeneralPurpose",
          "mode": "value"
        }
      ]
    },
    {
      "id": "T161",
      "name": "config",
      "kind": "method",
      "inputs": [
        {
          "type": "&base64::engine::general_purpose::GeneralPurpose",
          "name": "self",
          "mode": "&"
        }
      ],
      "outputs": [
        {
          "type": "Config",
          "mode": "&"
        }
      ]
    },
    {
      "id": "T162",
      "name": "encode",
      "kind": "method",
      "inputs": [
        {
          "type": "T",
          "name": "input",
          "mode": "value"
        },
        {
          "type": "&base64::engine::general_purpose::GeneralPurpose",
          "name": "self",
          "mode": "&"
        }
      ],
      "outputs": [
        {
          "type": "String",
          "mode": "value"
        }
      ],
      "generic_params": [
        "T: AsRef<[u8]>"
      ]
    },
    {
      "id": "T163",
      "name": "encode_string",
      "kind": "method",
      "inputs": [
        {
          "type": "&mut String",
          "name": "output_buf",
          "mode": "&mut"
        },
        {
          "type": "T",
          "name": "input",
          "mode": "value"
        },
        {
          "type": "&base64::engine::general_purpose::GeneralPurpose",
          "name": "self",
          "mode": "&"
        }
      ],
      "generic_params": [
        "T: AsRef<[u8]>"
      ]
    },
    {
      "id": "T164",
      "name": "encode_slice",
      "kind": "method",
      "inputs": [
        {
          "type": "&mut [u8]",
          "name": "output_buf",
          "mode": "&mut"
        },
        {
          "type": "T",
          "name": "input",
          "mode": "value"
        },
        {
          "type": "&base64::engine::general_purpose::GeneralPurpose",
          "name": "self",
          "mode": "&"
        }
      ],
      "outputs": [
        {
          "type": "Result",
          "mode": "value"
        }
      ],
      "generic_params": [
        "T: AsRef<[u8]>"
      ]
    },
    {
      "id": "T165",
      "name": "decode",
      "kind": "method",
      "inputs": [
        {
          "type": "T",
          "name": "input",
          "mode": "value"
        },
        {
          "type": "&base64::engine::general_purpose::GeneralPurpose",
          "name": "self",
          "mode": "&"
        }
      ],
      "outputs": [
        {
          "type": "Result",
          "mode": "value"
        }
      ],
      "generic_params": [
        "T: AsRef<[u8]>"
      ]
    },
    {
      "id": "T166",
      "name": "decode_vec",
      "kind": "method",
      "inputs": [
        {
          "type": "T",
          "name": "input",
          "mode": "value"
        },
        {
          "type": "&base64::engine::general_purpose::GeneralPurpose",
          "name": "self",
          "mode": "&"
        }
      ],
      "outputs": [
        {
          "type": "Result",
          "mode": "value"
        }
      ],
      "generic_params": [
        "T: AsRef<[u8]>"
      ]
    },
    {
      "id": "T167",
      "name": "decode_slice",
      "kind": "method",
      "inputs": [
        {
          "type": "&mut [u8]",
          "name": "output",
          "mode": "&mut"
        },
        {
          "type": "T",
          "name": "input",
          "mode": "value"
        },
        {
          "type": "&base64::engine::general_purpose::GeneralPurpose",
          "name": "self",
          "mode": "&"
        }
      ],
      "outputs": [
        {
          "type": "Result",
          "mode": "value"
        }
      ],
      "generic_params": [
        "T: AsRef<[u8]>"
      ]
    },
    {
      "id": "T168",
      "name": "decode_slice_unchecked",
      "kind": "method",
      "inputs": [
        {
          "type": "&mut [u8]",
          "name": "output",
          "mode": "&mut"
        },
        {
          "type": "T",
          "name": "input",
          "mode": "value"
        },
        {
          "type": "&base64::engine::general_purpose::GeneralPurpose",
          "name": "self",
          "mode": "&"
        }
      ],
      "outputs": [
        {
          "type": "Result",
          "mode": "value"
        }
      ],
      "generic_params": [
        "T: AsRef<[u8]>"
      ]
    },
    {
      "id": "T169",
      "name": "new",
      "kind": "method",
      "outputs": [
        {
          "type": "EncoderWriter",
          "mode": "value"
        }
      ],
      "generic_params": [
        "''e",
        "E: Engine",
        "W: io::Write"
      ]
    },
    {
      "id": "T170",
      "name": "finish",
      "kind": "method",
      "inputs": [
        {
          "type": "&mut base64::write::encoder::EncoderWriter<'e, E, W>",
          "name": "self",
          "mode": "&mut"
        }
      ],
      "outputs": [
        {
          "type": "Result",
          "mode": "value"
        }
      ],
      "generic_params": [
        "''e",
        "E: Engine",
        "W: io::Write"
      ]
    },
    {
      "id": "T171",
      "name": "into_inner",
      "kind": "method",
      "inputs": [
        {
          "type": "base64::write::encoder::EncoderWriter<'e, E, W>",
          "name": "self",
          "mode": "value"
        }
      ],
      "generic_params": [
        "''e",
        "E: Engine",
        "W: io::Write"
      ]
    },
    {
      "id": "T172",
      "name": "borrow",
      "kind": "method",
      "inputs": [
        {
          "type": "&base64::write::encoder::EncoderWriter<'e, E, W>",
          "name": "self",
          "mode": "&"
        }
      ],
      "generic_params": [
        "T"
      ]
    },
    {
      "id": "T173",
      "name": "borrow_mut",
      "kind": "method",
      "inputs": [
        {
          "type": "&mut base64::write::encoder::EncoderWriter<'e, E, W>",
          "name": "self",
          "mode": "&mut"
        }
      ],
      "generic_params": [
        "T"
      ]
    },
    {
      "id": "T174",
      "name": "into",
      "kind": "method",
      "inputs": [
        {
          "type": "base64::write::encoder::EncoderWriter<'e, E, W>",
          "name": "self",
          "mode": "value"
        }
      ],
      "generic_params": [
        "T",
        "U"
      ]
    },
    {
      "id": "T175",
      "name": "from",
      "kind": "method",
      "generic_params": [
        "T"
      ]
    },
    {
      "id": "T176",
      "name": "try_into",
      "kind": "method",
      "inputs": [
        {
          "type": "base64::write::encoder::EncoderWriter<'e, E, W>",
          "name": "self",
          "mode": "value"
        }
      ],
      "outputs": [
        {
          "type": "Error>",
          "mode": "value"
        }
      ],
      "generic_params": [
        "T",
        "U"
      ]
    },
    {
      "id": "T177",
      "name": "try_from",
      "kind": "method",
      "outputs": [
        {
          "type": "Error>",
          "mode": "value"
        }
      ],
      "generic_params": [
        "T",
        "U"
      ]
    },
    {
      "id": "T178",
      "name": "type_id",
      "kind": "method",
      "inputs": [
        {
          "type": "&base64::write::encoder::EncoderWriter<'e, E, W>",
          "name": "self",
          "mode": "&"
        }
      ],
      "outputs": [
        {
          "type": "TypeId",
          "mode": "value"
        }
      ],
      "generic_params": [
        "T"
      ]
    },
    {
      "id": "T179",
      "name": "fmt",
      "kind": "method",
      "inputs": [
        {
          "type": "&mut fmt::Formatter<'_>",
          "name": "f",
          "mode": "&mut"
        },
        {
          "type": "&base64::write::encoder::EncoderWriter<'e, E, W>",
          "name": "self",
          "mode": "&"
        }
      ],
      "outputs": [
        {
          "type": "Result",
          "mode": "value"
        }
      ],
      "generic_params": [
        "''e",
        "E: Engine",
        "W: io::Write"
      ]
    },
    {
      "id": "T180",
      "name": "write",
      "kind": "method",
      "inputs": [
        {
          "type": "&[u8]",
          "name": "input",
          "mode": "&"
        },
        {
          "type": "&mut base64::write::encoder::EncoderWriter<'e, E, W>",
          "name": "self",
          "mode": "&mut"
        }
      ],
      "outputs": [
        {
          "type": "Result",
          "mode": "value"
        }
      ],
      "generic_params": [
        "''e",
        "E: Engine",
        "W: io::Write"
      ]
    },
    {
      "id": "T181",
      "name": "flush",
      "kind": "method",
      "inputs": [
        {
          "type": "&mut base64::write::encoder::EncoderWriter<'e, E, W>",
          "name": "self",
          "mode": "&mut"
        }
      ],
      "outputs": [
        {
          "type": "Result",
          "mode": "value"
        }
      ],
      "generic_params": [
        "''e",
        "E: Engine",
        "W: io::Write"
      ]
    },
    {
      "id": "T182",
      "name": "drop",
      "kind": "method",
      "inputs": [
        {
          "type": "&mut base64::write::encoder::EncoderWriter<'e, E, W>",
          "name": "self",
          "mode": "&mut"
        }
      ],
      "generic_params": [
        "''e",
        "E: Engine",
        "W: io::Write"
      ]
    },
    {
      "id": "T183",
      "name": "decode_engine_slice",
      "kind": "function",
      "inputs": [
        {
          "type": "&mut [u8]",
          "name": "output",
          "mode": "&mut"
        }
      ],
      "outputs": [
        {
          "type": "Result",
          "mode": "value"
        }
      ],
      "generic_params": [
        "E: Engine",
        "T: AsRef<[u8]>"
      ],
      "origin": {
        "def_location": "base64::decode::decode_engine_slice"
      }
    },
    {
      "id": "T184",
      "name": "decode",
      "kind": "function",
      "generic_params": [
        "T: AsRef<[u8]>"
      ],
      "origin": {
        "def_location": "base64::decode::decode"
      }
    },
    {
      "id": "T185",
      "name": "consume",
      "kind": "function",
      "inputs": [
        {
          "type": "&str",
          "name": "buf",
          "mode": "&"
        }
      ]
    },
    {
      "id": "T186",
      "name": "decode_engine",
      "kind": "function",
      "generic_params": [
        "E: Engine",
        "T: AsRef<[u8]>"
      ],
      "origin": {
        "def_location": "base64::decode::decode_engine"
      }
    },
    {
      "id": "T187",
      "name": "encode",
      "kind": "function",
      "outputs": [
        {
          "type": "String",
          "mode": "value"
        }
      ],
      "generic_params": [
        "T: AsRef<[u8]>"
      ],
      "origin": {
        "def_location": "base64::encode::encode"
      }
    },
    {
      "id": "T188",
      "name": "encode_engine_string",
      "kind": "function",
      "inputs": [
        {
          "type": "&mut alloc::string::String",
          "name": "output_buf",
          "mode": "&mut"
        }
      ],
      "generic_params": [
        "E: Engine",
        "T: AsRef<[u8]>"
      ],
      "origin": {
        "def_location": "base64::encode::encode_engine_string"
      }
    },
    {
      "id": "T189",
      "name": "encoded_len",
      "kind": "function",
      "inputs": [
        {
          "type": "bool",
          "name": "padding",
          "mode": "value"
        },
        {
          "type": "usize",
          "name": "bytes_len",
          "mode": "value"
        }
      ],
      "outputs": [
        {
          "type": "Option",
          "mode": "value"
        }
      ],
      "origin": {
        "def_location": "base64::encode::encoded_len"
      }
    },
    {
      "id": "T190",
      "name": "encode_engine_slice",
      "kind": "function",
      "inputs": [
        {
          "type": "&mut [u8]",
          "name": "output_buf",
          "mode": "&mut"
        }
      ],
      "outputs": [
        {
          "type": "Result",
          "mode": "value"
        }
      ],
      "generic_params": [
        "E: Engine",
        "T: AsRef<[u8]>"
      ],
      "origin": {
        "def_location": "base64::encode::encode_engine_slice"
      }
    },
    {
      "id": "T191",
      "name": "decode_engine_vec",
      "kind": "function",
      "outputs": [
        {
          "type": "Result",
          "mode": "value"
        }
      ],
      "generic_params": [
        "E: Engine",
        "T: AsRef<[u8]>"
      ],
      "origin": {
        "def_location": "base64::decode::decode_engine_vec"
      }
    },
    {
      "id": "T192",
      "name": "encode_engine",
      "kind": "function",
      "outputs": [
        {
          "type": "String",
          "mode": "value"
        }
      ],
      "generic_params": [
        "E: Engine",
        "T: AsRef<[u8]>"
      ],
      "origin": {
        "def_location": "base64::encode::encode_engine"
      }
    },
    {
      "id": "T193",
      "name": "decoded_len_estimate",
      "kind": "function",
      "inputs": [
        {
          "type": "usize",
          "name": "encoded_len",
          "mode": "value"
        }
      ],
      "outputs": [
        {
          "type": "usize",
          "mode": "value"
        }
      ],
      "origin": {
        "def_location": "base64::decode::decoded_len_estimate"
      }
    },
    {
      "id": "T194",
      "name": "consume",
      "kind": "function",
      "inputs": [
        {
          "type": "&str",
          "name": "buf",
          "mode": "&"
        }
      ]
    },
    {
      "id": "T195",
      "name": "Option::unwrap_some(usize)",
      "kind": "function",
      "inputs": [
        {
          "type": "Option<usize>",
          "name": "option",
          "mode": "value"
        }
      ],
      "outputs": [
        {
          "type": "usize",
          "mode": "value"
        }
      ]
    },
    {
      "id": "T196",
      "name": "Option::unwrap_none()",
      "kind": "function",
      "inputs": [
        {
          "type": "Option<T>",
          "name": "option",
          "mode": "value"
        }
      ],
      "outputs": [
        {
          "type": "()",
          "mode": "value"
        }
      ]
    },
    {
      "id": "T197",
      "name": "Result::unwrap_ok()",
      "kind": "function",
      "inputs": [
        {
          "type": "Result<(), DecodeError>",
          "name": "result",
          "mode": "value"
        }
      ],
      "outputs": [
        {
          "type": "()",
          "mode": "value"
        }
      ]
    },
    {
      "id": "T198",
      "name": "Result::unwrap_err()",
      "kind": "function",
      "inputs": [
        {
          "type": "Result<(), DecodeError>",
          "name": "result",
          "mode": "value"
        }
      ],
      "outputs": [
        {
          "type": "DecodeError",
          "mode": "value"
        }
      ]
    },
    {
      "id": "T199",
      "name": "Result::unwrap_err()",
      "kind": "function",
      "inputs": [
        {
          "type": "Result<Vec<u8>, DecodeError>",
          "name": "result",
          "mode": "value"
        }
      ],
      "outputs": [
        {
          "type": "DecodeError",
          "mode": "value"
        }
      ]
    },
    {
      "id": "T200",
      "name": "Result::unwrap_ok()",
      "kind": "function",
      "inputs": [
        {
          "type": "Result<usize, DecodeError>",
          "name": "result",
          "mode": "value"
        }
      ],
      "outputs": [
        {
          "type": "usize",
          "mode": "value"
        }
      ]
    },
    {
      "id": "T201",
      "name": "Result::unwrap_err()",
      "kind": "function",
      "inputs": [
        {
          "type": "Result<usize, DecodeError>",
          "name": "result",
          "mode": "value"
        }
      ],
      "outputs": [
        {
          "type": "DecodeError",
          "mode": "value"
        }
      ]
    },
    {
      "id": "T202",
      "name": "Result::unwrap_ok()",
      "kind": "function",
      "inputs": [
        {
          "type": "Result<usize, DecodeSliceError>",
          "name": "result",
          "mode": "value"
        }
      ],
      "outputs": [
        {
          "type": "usize",
          "mode": "value"
        }
      ]
    },
    {
      "id": "T203",
      "name": "Result::unwrap_err()",
      "kind": "function",
      "inputs": [
        {
          "type": "Result<usize, DecodeSliceError>",
          "name": "result",
          "mode": "value"
        }
      ],
      "outputs": [
        {
          "type": "DecodeSliceError",
          "mode": "value"
        }
      ]
    },
    {
      "id": "T204",
      "name": "Result::unwrap_ok()",
      "kind": "function",
      "inputs": [
        {
          "type": "Result<usize, EncodeSliceError>",
          "name": "result",
          "mode": "value"
        }
      ],
      "outputs": [
        {
          "type": "usize",
          "mode": "value"
        }
      ]
    },
    {
      "id": "T205",
      "name": "Result::unwrap_err()",
      "kind": "function",
      "inputs": [
        {
          "type": "Result<usize, EncodeSliceError>",
          "name": "result",
          "mode": "value"
        }
      ],
      "outputs": [
        {
          "type": "EncodeSliceError",
          "mode": "value"
        }
      ]
    }
  ],
  "guards": [],
  "metadata": {}
}